databloom/__init__.py
databloom/metadata.py
databloom/utils_duckdb.py
databloom/version.py
databloom/warehouse.py
databloom/api/__init__.py
databloom/api/credentials.py
databloom/api/db_connector.py
databloom/api/nessie_metadata.py
databloom/core/__init__.py
databloom/core/context.py
databloom/core/databloom_context.py
databloom/core/dataset.py
databloom/core/duckdb_utils.py
databloom/core/lighter_context.py
databloom/core/connector/__init__.py
databloom/core/connector/duckdb.py
databloom/core/connector/ggsheet.py
databloom/core/connector/mongodb.py
databloom/core/connector/mysql.py
databloom/core/connector/postgresql.py
databloom/core/connector/spark_postgresql.py
databloom/core/dataset/__init__.py
databloom/core/dataset/dataset.py
databloom/core/dataset/duckdb.py
databloom/core/spark/__init__.py
databloom/core/spark/decorators.py
databloom/core/spark/session.py
databloom/dataset/__init__.py
databloom/dataset/dataset.py
databloom-2.1.23.dist-info/METADATA
databloom-2.1.23.dist-info/WHEEL
databloom-2.1.23.dist-info/top_level.txt
databloom-2.1.23.dist-info/RECORD
